{"component_type":"converter","config_json":{"version":"1.0.0","metadata":{"title":"Convert Hertz to RPM – Frequency to Rotation Converter","description":"Convert frequency from Hertz (Hz) to Revolutions Per Minute (RPM), useful for machinery specifications."},"logic":{"type":"conversion","fromUnitId":"hertz","toUnitId":"rpm"},"page_content":{"introduction":["This converter transforms frequency in hertz to mechanical rotation rate in RPM.","Machinery specifications use RPM while frequency measured in Hz.","This converter uses the relationship where 1 Hz equals 60 RPM."],"methodology":["1 Hz = 60 RPM. To convert Hz to RPM, multiply by 60.","Machinery speeds commonly expressed in RPM for practical understanding.","Understanding Hz to RPM conversion is essential for mechanical engineering.","This converter provides precise rotation rate conversion."],"examples":["Example 1 – Electric motor: 50 Hz = 3,000 RPM.","Example 2 – Car engine: 80 Hz = 4,800 RPM.","Example 3 – Fan: 20 Hz = 1,200 RPM."],"faqs":[{"question":"What does RPM mean?","answer":"Revolutions Per Minute. How many full rotations per minute."},{"question":"What's a typical motor speed?","answer":"AC motors: 1,200-3,600 RPM. DC motors: variable. Fans: 800-3,000 RPM."},{"question":"Why convert Hz to RPM?","answer":"Electrical frequency (Hz) differs from mechanical output (RPM) by gear ratios."},{"question":"What's the relationship between Hz and electrical frequency?","answer":"50 Hz electricity: ~1,500-3,000 RPM AC motor (pole dependent). 60 Hz: similar."},{"question":"How do gears affect RPM?","answer":"Gear ratio = input RPM / output RPM. 2:1 ratio halves RPM, doubles torque."},{"question":"What's torque vs RPM?","answer":"Torque: rotational force. RPM: rotation speed. Power = Torque × RPM."},{"question":"How do I increase motor speed?","answer":"Variable frequency drive changes Hz input. Direct: no simple way."},{"question":"What's critical RPM?","answer":"Resonance frequency where vibration amplifies. Must avoid during operation."}],"citations":[{"label":"Motor Specifications","url":"https://www.nema.org/"},{"label":"Mechanical Engineering","url":"https://www.asme.org/"},{"label":"Electrical Standards","url":"https://www.ieee.org/"},{"label":"Frequency Standards","url":"https://www.nist.gov/"},{"label":"Equipment Manuals","url":"https://www.iso.org/"}],"glossary":[{"term":"Hertz (Hz)","definition":"Frequency: cycles per second."},{"term":"RPM","definition":"Revolutions Per Minute: rotations per minute."},{"term":"Torque","definition":"Rotational force, measured in newton-meters."},{"term":"Power","definition":"Rate of energy use: watts = torque × angular velocity."},{"term":"Gear Ratio","definition":"Output/input speed relationship in mechanical transmission."}]},"links":{"internal":["/conversions/frequency/rpm-to-hertz-converter"],"external":[]},"schema":{"additionalTypes":["HowTo"]}}}
